gumpclock/__init__.py
gumpclock/app.py
gumpclock/core.py
gumpclock-0.1.1.dist-info/licenses/License.txt
gumpclock-0.1.1.dist-info/METADATA
gumpclock-0.1.1.dist-info/WHEEL
gumpclock-0.1.1.dist-info/entry_points.txt
gumpclock-0.1.1.dist-info/top_level.txt
gumpclock-0.1.1.dist-info/RECORD
