Metadata-Version: 2.4
Name: gumpclock
Version: 0.1.1
Summary: A new time counting system with Tkinter GUI
Author: EuropeanSwallow
Keywords: time,gump,tkinter,clock
License-File: License.txt
Dynamic: license-file
